{
	"configurations" : 
	[
		{
			"directories" : 
			[
				{
					"build" : ".",
					"childIndexes" : 
					[
						1
					],
					"hasInstallRule" : true,
					"jsonFile" : "directory-.-Debug-d0094a50bb2071803777.json",
					"minimumCMakeVersion" : 
					{
						"string" : "3.21"
					},
					"projectIndex" : 0,
					"source" : ".",
					"targetIndexes" : 
					[
						4,
						5
					]
				},
				{
					"build" : "lib/googletest-1.14.0",
					"childIndexes" : 
					[
						2
					],
					"hasInstallRule" : true,
					"jsonFile" : "directory-lib.googletest-1.14.0-Debug-002f5dc9b059812ba008.json",
					"minimumCMakeVersion" : 
					{
						"string" : "3.13"
					},
					"parentIndex" : 0,
					"projectIndex" : 1,
					"source" : "lib/googletest-1.14.0"
				},
				{
					"build" : "lib/googletest-1.14.0/googlemock",
					"childIndexes" : 
					[
						3
					],
					"hasInstallRule" : true,
					"jsonFile" : "directory-lib.googletest-1.14.0.googlemock-Debug-0d05cdd37a2cdf98afa2.json",
					"minimumCMakeVersion" : 
					{
						"string" : "3.13"
					},
					"parentIndex" : 1,
					"projectIndex" : 2,
					"source" : "lib/googletest-1.14.0/googlemock",
					"targetIndexes" : 
					[
						0,
						1
					]
				},
				{
					"build" : "lib/googletest-1.14.0/googletest",
					"hasInstallRule" : true,
					"jsonFile" : "directory-lib.googletest-1.14.0.googletest-Debug-aa98fa3f9fae41f10164.json",
					"minimumCMakeVersion" : 
					{
						"string" : "3.13"
					},
					"parentIndex" : 2,
					"projectIndex" : 3,
					"source" : "lib/googletest-1.14.0/googletest",
					"targetIndexes" : 
					[
						2,
						3
					]
				}
			],
			"name" : "Debug",
			"projects" : 
			[
				{
					"childIndexes" : 
					[
						1
					],
					"directoryIndexes" : 
					[
						0
					],
					"name" : "ProjectPart1",
					"targetIndexes" : 
					[
						4,
						5
					]
				},
				{
					"childIndexes" : 
					[
						2
					],
					"directoryIndexes" : 
					[
						1
					],
					"name" : "googletest-distribution",
					"parentIndex" : 0
				},
				{
					"childIndexes" : 
					[
						3
					],
					"directoryIndexes" : 
					[
						2
					],
					"name" : "gmock",
					"parentIndex" : 1,
					"targetIndexes" : 
					[
						0,
						1
					]
				},
				{
					"directoryIndexes" : 
					[
						3
					],
					"name" : "gtest",
					"parentIndex" : 2,
					"targetIndexes" : 
					[
						2,
						3
					]
				}
			],
			"targets" : 
			[
				{
					"directoryIndex" : 2,
					"id" : "gmock::@2d8689975312a5537110",
					"jsonFile" : "target-gmock-Debug-df882d14730f89652491.json",
					"name" : "gmock",
					"projectIndex" : 2
				},
				{
					"directoryIndex" : 2,
					"id" : "gmock_main::@2d8689975312a5537110",
					"jsonFile" : "target-gmock_main-Debug-958030bbb7d41cad8586.json",
					"name" : "gmock_main",
					"projectIndex" : 2
				},
				{
					"directoryIndex" : 3,
					"id" : "gtest::@a0ac9289cd92a5e60ec4",
					"jsonFile" : "target-gtest-Debug-717bad4b4cbc4a23af35.json",
					"name" : "gtest",
					"projectIndex" : 3
				},
				{
					"directoryIndex" : 3,
					"id" : "gtest_main::@a0ac9289cd92a5e60ec4",
					"jsonFile" : "target-gtest_main-Debug-716ca59fbd6258e6c6e4.json",
					"name" : "gtest_main",
					"projectIndex" : 3
				},
				{
					"directoryIndex" : 0,
					"id" : "run_app::@6890427a1f51a3e7e1df",
					"jsonFile" : "target-run_app-Debug-8c61ee0c0c6a04e87c7e.json",
					"name" : "run_app",
					"projectIndex" : 0
				},
				{
					"directoryIndex" : 0,
					"id" : "run_tests::@6890427a1f51a3e7e1df",
					"jsonFile" : "target-run_tests-Debug-f9e3ddc9ff148a76d131.json",
					"name" : "run_tests",
					"projectIndex" : 0
				}
			]
		}
	],
	"kind" : "codemodel",
	"paths" : 
	{
		"build" : "C:/Users/PopovArtem/CLionProjects/ProjectPart1/cmake-build-debug",
		"source" : "C:/Users/PopovArtem/CLionProjects/ProjectPart1"
	},
	"version" : 
	{
		"major" : 2,
		"minor" : 4
	}
}
